Workbook

Sheet Assumptions
A1: Eventra pricing sheet: assumptions
A2: Yellow cells are inputs. Change them and every other sheet updates. Prices marked 'verify' are estimates: check the provider's pricing page.
A3: Item | B3: Value | C3: Note
A4: US dollar to rupee rate | B4: 88 | C4: Change to today's rate.
A5: GST you charge customers | B5: 0.18 | C5: 18% GST on services. It is collected for the government, not your income. Needs GST registration above the limit.
A6: Payment gateway fee (incl. GST on the fee) | B6: 0.0236 | C6: About 2% Razorpay fee plus 18% GST on that fee. Verify.
A7: Video data per viewer per hour (GB) | B7: 0.45 | C7: About 1 Mbps at 720p = 0.45 GB per hour. Data saver or audio-only is lower (see Costs sheet).
A8: AWS data transfer out, per GB (USD) | B8: 0.1093 | C8: Approx. Mumbai region, after the free 100 GB a month. Verify on the AWS pricing page.
A9: Safety margin added to costs | B9: 0.15 | C9: Covers retries, extra viewers, small price changes.
A10: Cloudflare R2 storage, per GB per month (USD) | B10: 0.015 | C10: Photos, cards, videos, sponsor logos. Downloads by guests cost nothing on R2.
A11: Months you keep an event's files | B11: 3 | C11: Used to cost the stored files.
A12: Target profit margin | B12: 0.6 | C12: Used for the suggested minimum price.
A14: Fixed monthly costs (paid whether or not you have events)
A15: Item | B15: Value | C15: Note
A16: AWS server running LiveKit, per month (USD) | B16: 62 | C16: Example: a 2 vCPU compute instance on demand in Mumbai. Verify. You can shut it down between events and pay per hour.
A17: Vercel Pro, per month (USD) | B17: 20 | C17: The free Hobby plan is for personal use. A paid product should use Pro. Verify.
A18: Neon database, per month (USD) | B18: 19 | C18: There is a free plan. A paid plan gives more room. Verify.
A19: Domain, per year (INR) | B19: 800 | C19: A .in domain is roughly this. Verify.
A20: Cloudflare other (DNS, R2 base), per month (USD) | B20: 0 | C20: R2's free 10 GB and free downloads cover small use.
A21: Other tools and support, per month (INR) | B21: 500 | C21: Email, phone, anything else.

Sheet Costs
A1: Cost to you for one event (AWS live video + Cloudflare R2 files)
A2: Live video is the big cost: AWS charges for every GB sent to viewers. Cloudflare R2 only stores files and does not help with live bandwidth.
A3: Scenario | B3: Free plan | C3: Small | D3: Standard | E3: Premium | F3: Festival day | G3: 10-day festival
A4: Viewers watching at the same time | B4: 20 | C4: 50 | D4: 100 | E4: 300 | F4: 500 | G4: 200
A5: Hours streamed (total) | B5: 1 | C5: 2 | D5: 3 | E5: 4 | F5: 6 | G5: 30
A6: Share of time viewers are actually watching | B6: 0.7 | C6: 0.7 | D6: 0.7 | E6: 0.7 | F6: 0.7 | G6: 0.7
A7: Quality factor (1 = 720p, 0.5 = 480p, 0.1 = audio only) | B7: 1 | C7: 1 | D7: 1 | E7: 1 | F7: 0.5 | G7: 0.3
A8: Files stored: photos, video, card (GB) | B8: 1 | C8: 2 | D8: 5 | E8: 10 | F8: 10 | G8: 5
A9: Viewer-hours | B9: =B4*B5*B6 | C9: =C4*C5*C6 | D9: =D4*D5*D6 | E9: =E4*E5*E6 | F9: =F4*F5*F6 | G9: =G4*G5*G6
A10: Video sent to viewers (GB) | B10: =B9*B7*Assumptions!$B$7 | C10: =C9*C7*Assumptions!$B$7 | D10: =D9*D7*Assumptions!$B$7 | E10: =E9*E7*Assumptions!$B$7 | F10: =F9*F7*Assumptions!$B$7 | G10: =G9*G7*Assumptions!$B$7
A11: AWS bandwidth cost (USD) | B11: =B10*Assumptions!$B$8 | C11: =C10*Assumptions!$B$8 | D11: =D10*Assumptions!$B$8 | E11: =E10*Assumptions!$B$8 | F11: =F10*Assumptions!$B$8 | G11: =G10*Assumptions!$B$8
A12: Cloudflare R2 storage cost (USD) | B12: =B8*Assumptions!$B$10*Assumptions!$B$11 | C12: =C8*Assumptions!$B$10*Assumptions!$B$11 | D12: =D8*Assumptions!$B$10*Assumptions!$B$11 | E12: =E8*Assumptions!$B$10*Assumptions!$B$11 | F12: =F8*Assumptions!$B$10*Assumptions!$B$11 | G12: =G8*Assumptions!$B$10*Assumptions!$B$11
A13: Subtotal (USD) | B13: =B11+B12 | C13: =C11+C12 | D13: =D11+D12 | E13: =E11+E12 | F13: =F11+F12 | G13: =G11+G12
A14: Safety margin (USD) | B14: =B13*Assumptions!$B$9 | C14: =C13*Assumptions!$B$9 | D14: =D13*Assumptions!$B$9 | E14: =E13*Assumptions!$B$9 | F14: =F13*Assumptions!$B$9 | G14: =G13*Assumptions!$B$9
A15: Total cost (USD) | B15: =B13+B14 | C15: =C13+C14 | D15: =D13+D14 | E15: =E13+E14 | F15: =F13+F14 | G15: =G13+G14
A16: TOTAL COST TO YOU (INR) | B16: =B15*Assumptions!$B$4 | C16: =C15*Assumptions!$B$4 | D16: =D15*Assumptions!$B$4 | E16: =E15*Assumptions!$B$4 | F16: =F15*Assumptions!$B$4 | G16: =G15*Assumptions!$B$4
A18: Reading this: the 10-day festival uses audio-first (0.3) to show how a charity event can stay affordable. Set the quality factor to 1 to see the full-video cost.

Sheet Pricing
A1: What to charge and what you earn per event
A2: Type your price in the yellow cells (before GST). Profit here is per event, before fixed monthly costs.
A3: Plan | B3: Your cost (INR) | C3: Price before GST (INR) | D3: GST (INR) | E3: Customer pays (INR) | F3: Gateway fee (INR) | G3: You keep before cost (INR) | H3: PROFIT per event (INR) | I3: Margin | J3: Min price for target margin | K3: Note
A4: Free plan | B4: =Costs!B16 | C4: 0 | D4: =C4*Assumptions!$B$5 | E4: =C4+D4 | F4: =E4*Assumptions!$B$6 | G4: =C4-F4 | H4: =G4-B4 | I4: =IF(C4=0,"n/a",H4/C4) | J4: =ROUNDUP(B4/(1-Assumptions!$B$12-(1+Assumptions!$B$5)*Assumptions!$B$6)/50,0)*50 | K4: Brings users in. Capped at 20 viewers for 1 hour.
A5: Small | B5: =Costs!C16 | C5: 999 | D5: =C5*Assumptions!$B$5 | E5: =C5+D5 | F5: =E5*Assumptions!$B$6 | G5: =C5-F5 | H5: =G5-B5 | I5: =IF(C5=0,"n/a",H5/C5) | J5: =ROUNDUP(B5/(1-Assumptions!$B$12-(1+Assumptions!$B$5)*Assumptions!$B$6)/50,0)*50 | K5: Birthday, small pooja.
A6: Standard | B6: =Costs!D16 | C6: 2999 | D6: =C6*Assumptions!$B$5 | E6: =C6+D6 | F6: =E6*Assumptions!$B$6 | G6: =C6-F6 | H6: =G6-B6 | I6: =IF(C6=0,"n/a",H6/C6) | J6: =ROUNDUP(B6/(1-Assumptions!$B$12-(1+Assumptions!$B$5)*Assumptions!$B$6)/50,0)*50 | K6: Typical wedding.
A7: Premium | B7: =Costs!E16 | C7: 11999 | D7: =C7*Assumptions!$B$5 | E7: =C7+D7 | F7: =E7*Assumptions!$B$6 | G7: =C7-F7 | H7: =G7-B7 | I7: =IF(C7=0,"n/a",H7/C7) | J7: =ROUNDUP(B7/(1-Assumptions!$B$12-(1+Assumptions!$B$5)*Assumptions!$B$6)/50,0)*50 | K7: Large wedding or hall event.
A8: Festival day | B8: =Costs!F16 | C8: 14999 | D8: =C8*Assumptions!$B$5 | E8: =C8+D8 | F8: =E8*Assumptions!$B$6 | G8: =C8-F8 | H8: =G8-B8 | I8: =IF(C8=0,"n/a",H8/C8) | J8: =ROUNDUP(B8/(1-Assumptions!$B$12-(1+Assumptions!$B$5)*Assumptions!$B$6)/50,0)*50 | K8: Big public event. Quote each one.
A9: 10-day festival (charity) | B9: =Costs!G16 | C9: 0 | D9: =C9*Assumptions!$B$5 | E9: =C9+D9 | F9: =E9*Assumptions!$B$6 | G9: =C9-F9 | H9: =G9-B9 | I9: =IF(C9=0,"n/a",H9/C9) | J9: =ROUNDUP(B9/(1-Assumptions!$B$12-(1+Assumptions!$B$5)*Assumptions!$B$6)/50,0)*50 | K9: Price 0 means the loss shown is what sponsors or donations must cover.

Sheet Monthly
A1: Monthly view: how many events you need to make a profit
A2: Enter how many events of each type you expect in a month.
A3: Plan | B3: Events per month | C3: Profit per event (INR) | D3: Profit from these events (INR) | E3: Revenue before GST (INR)
A4: Free plan | B4: 20 | C4: =Pricing!H4 | D4: =B4*C4 | E4: =B4*Pricing!C4
A5: Small | B5: 10 | C5: =Pricing!H5 | D5: =B5*C5 | E5: =B5*Pricing!C5
A6: Standard | B6: 6 | C6: =Pricing!H6 | D6: =B6*C6 | E6: =B6*Pricing!C6
A7: Premium | B7: 2 | C7: =Pricing!H7 | D7: =B7*C7 | E7: =B7*Pricing!C7
A8: Festival day | B8: 1 | C8: =Pricing!H8 | D8: =B8*C8 | E8: =B8*Pricing!C8
A9: 10-day festival (charity) | B9: 0 | C9: =Pricing!H9 | D9: =B9*C9 | E9: =B9*Pricing!C9
A11: Fixed monthly costs (INR) | B11: =(Assumptions!B16+Assumptions!B17+Assumptions!B18+Assumptions!B20)*Assumptions!B4+Assumptions!B19/12+Assumptions!B21
A12: Profit from events (INR) | B12: =SUM(D4:D9)
A13: NET PROFIT PER MONTH (INR) | B13: =B12-B11
A14: Revenue per month before GST (INR) | B14: =SUM(E4:E9)
A15: Standard events needed to cover fixed costs | B15: =IF(Pricing!H6>0,ROUNDUP(B11/Pricing!H6,0),"price too low")
A17: Income tax is not included. Ask an accountant about GST filing and tax.

Sheet Notes
A1: Notes and limits of this sheet
A3: 1. Prices are estimates. AWS, Vercel, Neon and Razorpay rates change. Check each pricing page before you set real prices.
A4: 2. Live video bandwidth is the main cost. 100 people watching for 3 hours uses roughly 95 GB. At AWS rates that is about the cost shown on the Costs sheet.
A5: 3. AWS gives 100 GB of free data a month in total. This sheet ignores that to stay on the safe side, so real costs for small months are a little lower.
A6: 4. Cloudflare R2 is cheap for stored files and charges nothing for downloads, but it does not carry live video. Live video goes from your AWS server to viewers.
A7: 5. Ways to lower the live cost: lower video quality, audio-first mode for devotional events, a viewer cap per event, and tap-to-watch.
A8: 6. Using LiveKit Cloud instead of your own AWS server avoids server upkeep. Its Ship plan is $50 a month with data included up to 250 GB.
A9: 7. GST: charge 18% on top of your price and pass it on to the government. It is not profit. This sheet shows the customer's total including GST.
A10: 8. Fixed costs include a running AWS server. Switching the server off between events lowers this a lot.
A11: 9. Charity events: set the price to 0 and the sheet shows the loss that sponsors, donations or your own budget must cover.
A12: 10. This is a planning tool, not tax or legal advice.
